{"id":"1142620","archetype":"Affinity","url":"https://www.mtggoldfish.com/deck/1142620","pilot":"Lance Vest","place":"12th","tournament_name":"SCG Pauper Classic Roanoke","tournament_date":"2018-06-10","mtgo_price":29,"tabletop_price":73,"decklist":{"main":[{"qty":4,"name":"Atog"},{"qty":4,"name":"Carapace Forger"},{"qty":4,"name":"Chromatic Star"},{"qty":4,"name":"Darksteel Citadel"},{"qty":3,"name":"Flayer Husk"},{"qty":2,"name":"Fling"},{"qty":4,"name":"Frogmite"},{"qty":4,"name":"Galvanic Blast"},{"qty":1,"name":"Gearseeker Serpent"},{"qty":4,"name":"Great Furnace"},{"qty":2,"name":"Ichor Wellspring"},{"qty":1,"name":"Metallic Rebuke"},{"qty":4,"name":"Myr Enforcer"},{"qty":2,"name":"Prophetic Prism"},{"qty":4,"name":"Seat of the Synod"},{"qty":3,"name":"Springleaf Drum"},{"qty":2,"name":"Temur Battle Rage"},{"qty":4,"name":"Thoughtcast"},{"qty":4,"name":"Tree of Tales"}],"side":[{"qty":2,"name":"Electrickery"},{"qty":2,"name":"Feed the Clan"},{"qty":2,"name":"Gorilla Shaman"},{"qty":2,"name":"Hydroblast"},{"qty":2,"name":"Krark-Clan Shaman"},{"qty":3,"name":"Mountain"},{"qty":2,"name":"Relic of Progenitus"}]}}