{"id":"196144","archetype":"MonoB Control","url":"https://www.mtggoldfish.com/deck/196144","pilot":"blackhawk2009","place":"3 - 1","tournament_name":"Pauper Daily #5712185","tournament_date":"2013-07-21","mtgo_price":36,"tabletop_price":null,"decklist":{"main":[{"qty":3,"name":"Augur of Skulls"},{"qty":2,"name":"Barren Moor"},{"qty":2,"name":"Bojuka Bog"},{"qty":4,"name":"Chittering Rats"},{"qty":3,"name":"Crypt Rats"},{"qty":3,"name":"Cuombajj Witches"},{"qty":1,"name":"Dead Weight"},{"qty":2,"name":"Duress"},{"qty":1,"name":"Funeral Charm"},{"qty":4,"name":"Geth's Verdict"},{"qty":3,"name":"Liliana's Specter"},{"qty":2,"name":"Okiba-Gang Shinobi"},{"qty":3,"name":"Phyrexian Rager"},{"qty":3,"name":"Sign in Blood"},{"qty":19,"name":"Swamp"},{"qty":2,"name":"Tendrils of Corruption"},{"qty":3,"name":"Unearth"}],"side":[{"qty":2,"name":"Choking Sands"},{"qty":1,"name":"Corrupt"},{"qty":1,"name":"Devour Flesh"},{"qty":2,"name":"Duress"},{"qty":1,"name":"Echoing Decay"},{"qty":1,"name":"Funeral Charm"},{"qty":4,"name":"Rancid Earth"},{"qty":1,"name":"Snuff Out"},{"qty":1,"name":"Sorin's Thirst"},{"qty":1,"name":"Victim of Night"}]}}