{"id":"6215798","archetype":"MonoB Control","url":"https://www.mtggoldfish.com/deck/6215798","pilot":"DONkLE","place":"3 - 2","tournament_name":"BLUE - SAT - 1PM - Chicago Pauper Cup","tournament_date":"2024-02-24","mtgo_price":5,"tabletop_price":22,"decklist":{"main":[{"qty":2,"name":"Bone Picker"},{"qty":4,"name":"Deadly Dispute"},{"qty":2,"name":"Fanatical Offering"},{"qty":2,"name":"Fleshbag Marauder"},{"qty":2,"name":"Gray Merchant of Asphodel"},{"qty":2,"name":"Ichor Wellspring"},{"qty":2,"name":"Mephitic Draught"},{"qty":4,"name":"Nested Shambler"},{"qty":4,"name":"Okiba Reckoner Raid"},{"qty":2,"name":"Pestilence"},{"qty":2,"name":"Reckoner's Bargain"},{"qty":4,"name":"Serrated Scorpion"},{"qty":4,"name":"Sovereign's Bite"},{"qty":14,"name":"Swamp"},{"qty":4,"name":"Tithing Blade"},{"qty":2,"name":"Vampire's Kiss"},{"qty":4,"name":"Vault of Whispers"}],"side":[{"qty":2,"name":"Bone Shards"},{"qty":1,"name":"Bump in the Night"},{"qty":2,"name":"Cower in Fear"},{"qty":2,"name":"Duress"},{"qty":4,"name":"Hopeless Nightmare"},{"qty":2,"name":"Nihil Spellbomb"},{"qty":2,"name":"Seizures"}]}}