{"id":"865069","archetype":"Burn","url":"https://www.mtggoldfish.com/deck/865069","pilot":"AstroBonny","place":"5 - 0","tournament_name":"Pauper League 2017-12-20","tournament_date":"2017-12-20","mtgo_price":27,"tabletop_price":72,"decklist":{"main":[{"qty":4,"name":"Chain Lightning"},{"qty":4,"name":"Fireblast"},{"qty":4,"name":"Firebrand Archer"},{"qty":2,"name":"Forgotten Cave"},{"qty":4,"name":"Insolent Neonate"},{"qty":4,"name":"Keldon Marauders"},{"qty":4,"name":"Lava Spike"},{"qty":4,"name":"Lightning Bolt"},{"qty":4,"name":"Magma Jet"},{"qty":15,"name":"Mountain"},{"qty":4,"name":"Rift Bolt"},{"qty":4,"name":"Searing Blaze"},{"qty":3,"name":"Staggershock"}],"side":[{"qty":2,"name":"Curse of the Pierced Heart"},{"qty":2,"name":"Electrickery"},{"qty":2,"name":"Flaring Pain"},{"qty":3,"name":"Martyr of Ashes"},{"qty":2,"name":"Relic of Progenitus"},{"qty":4,"name":"Smash to Smithereens"}]}}