[{"id":"2928748","archetype":"Walls","pilot":"baricade91","place":"5 - 0","tournament_name":"Pauper League 2020-04-15","tournament_date":"2020-04-15"},{"id":"2935539","archetype":"Walls","pilot":"baricade91","place":"5 - 2","tournament_name":"Pauper Super Qualifier #12130316","tournament_date":"2020-04-14"},{"id":"2908419","archetype":"Walls","pilot":"infinitehippie","place":"5 - 0","tournament_name":"Pauper League 2020-04-08","tournament_date":"2020-04-08"},{"id":"2908420","archetype":"Walls","pilot":"Kirblinxy","place":"5 - 0","tournament_name":"Pauper League 2020-04-08","tournament_date":"2020-04-08"},{"id":"2850038","archetype":"Walls","pilot":"Kirblinxy","place":"5 - 0","tournament_name":"Pauper League 2020-03-18","tournament_date":"2020-03-18"},{"id":"2142850","archetype":"Walls","pilot":"pproteus","place":"5 - 0","tournament_name":"Pauper League 2019-07-31","tournament_date":"2019-07-31"},{"id":"2137126","archetype":"Walls","pilot":"pproteus","place":"4 - 3","tournament_name":"Pauper Challenge #11929200","tournament_date":"2019-07-28"}]