{
    "date": "2012-08-21",
    "deck_ids": [
        "155893",
        "155899",
        "155890",
        "155884",
        "155902",
        "155889",
        "155900",
        "155888",
        "155913",
        "155892",
        "155898",
        "155887",
        "155909",
        "155885",
        "155906",
        "155911",
        "155912",
        "155907",
        "155903",
        "155895",
        "155905",
        "155914",
        "155901",
        "155894",
        "155910",
        "155886",
        "155891",
        "155897",
        "155896",
        "155904",
        "155908"
    ],
    "name": "Pauper Daily #4213179",
    "py/object": "pauperformance_bot.entity.api.tournament.Tournament",
    "url": "https://www.mtggoldfish.com/tournament/10914"
}