{
    "date": "2025-05-17",
    "deck_ids": [
        "7111801",
        "7111802",
        "7111803",
        "7111804",
        "7111805",
        "7111806",
        "7111807",
        "7111808",
        "7111809",
        "7111810",
        "7111811",
        "7111812",
        "7111813",
        "7111814",
        "7111815",
        "7111816",
        "7111817",
        "7111818",
        "7111819",
        "7111820",
        "7111821",
        "7111822",
        "7111823",
        "7111824",
        "7111825",
        "7111826",
        "7111827",
        "7111828",
        "7111829",
        "7111830",
        "7111831",
        "7111832",
        "7111833",
        "7111834",
        "7111835",
        "7111836",
        "7111837",
        "7111838",
        "7111839",
        "7111840",
        "7111841",
        "7111842",
        "7111843",
        "7111844",
        "7111845",
        "7111846",
        "7111847",
        "7111848",
        "7111849",
        "7111850",
        "7111851",
        "7111852",
        "7111853",
        "7111854",
        "7111855",
        "7111856",
        "7111857",
        "7111858",
        "7111859",
        "7111860",
        "7111861",
        "7111862",
        "7111863",
        "7111864",
        "7111865"
    ],
    "name": "Axion Now Commoners Cup\n",
    "py/object": "pauperformance_bot.entity.api.tournament.Tournament",
    "url": "https://www.mtggoldfish.com/tournament/55875"
}