{"id":"177648","archetype":"Goblins","url":"https://www.mtggoldfish.com/deck/177648","pilot":"GarH","place":"3 - 1","tournament_name":"Pauper Daily #5019948","tournament_date":"2013-02-20","mtgo_price":42,"tabletop_price":null,"decklist":{"main":[{"qty":4,"name":"Chain Lightning"},{"qty":4,"name":"Foundry Street Denizen"},{"qty":3,"name":"Goblin Arsonist"},{"qty":4,"name":"Goblin Bushwhacker"},{"qty":4,"name":"Goblin Cohort"},{"qty":4,"name":"Goblin Sledder"},{"qty":4,"name":"Lightning Bolt"},{"qty":4,"name":"Mogg Conscripts"},{"qty":4,"name":"Mogg Raider"},{"qty":4,"name":"Mogg War Marshal"},{"qty":17,"name":"Mountain"},{"qty":4,"name":"Sparksmith"}],"side":[{"qty":3,"name":"Electrickery"},{"qty":3,"name":"Flame Jab"},{"qty":3,"name":"Gorilla Shaman"},{"qty":4,"name":"Pyroblast"},{"qty":2,"name":"Smash to Smithereens"}]}}