{"id":"2828510","archetype":"Bogles","url":"https://www.mtggoldfish.com/deck/2828510","pilot":"BERNASTORRES","place":"5 - 1","tournament_name":"Pauper Challenge #12102020","tournament_date":"2020-03-08","mtgo_price":41,"tabletop_price":45,"decklist":{"main":[{"qty":4,"name":"Abundant Growth"},{"qty":4,"name":"Ancestral Mask"},{"qty":4,"name":"Armadillo Cloak"},{"qty":2,"name":"Ash Barrens"},{"qty":2,"name":"Cartouche of Solidarity"},{"qty":2,"name":"Commune with the Gods"},{"qty":2,"name":"Crumbling Vestige"},{"qty":1,"name":"Dispel"},{"qty":4,"name":"Ethereal Armor"},{"qty":4,"name":"Gladecover Scout"},{"qty":2,"name":"Heliod's Pilgrim"},{"qty":1,"name":"Khalni Garden"},{"qty":3,"name":"Rancor"},{"qty":2,"name":"Silhana Ledgewalker"},{"qty":4,"name":"Slippery Bogle"},{"qty":12,"name":"Snow-Covered Forest"},{"qty":1,"name":"Snow-Covered Plains"},{"qty":2,"name":"Unbridled Growth"},{"qty":4,"name":"Utopia Sprawl"}],"side":[{"qty":2,"name":"Crimson Acolyte"},{"qty":2,"name":"Dispel"},{"qty":2,"name":"Electrickery"},{"qty":2,"name":"Gut Shot"},{"qty":1,"name":"Lifelink"},{"qty":2,"name":"Natural State"},{"qty":2,"name":"Nature's Claim"},{"qty":2,"name":"Standard Bearer"}]}}