{"id":"4599634","archetype":"Affinity","url":"https://www.mtggoldfish.com/deck/4599634","pilot":"Mogged","place":"16th","tournament_name":"Pauper Challenge #12383938","tournament_date":"2022-02-06","mtgo_price":69,"tabletop_price":67,"decklist":{"main":[{"qty":4,"name":"Blood Fountain"},{"qty":4,"name":"Chromatic Star"},{"qty":2,"name":"Darksteel Citadel"},{"qty":4,"name":"Deadly Dispute"},{"qty":4,"name":"Disciple of the Vault"},{"qty":4,"name":"Drossforge Bridge"},{"qty":4,"name":"Frogmite"},{"qty":4,"name":"Galvanic Blast"},{"qty":4,"name":"Great Furnace"},{"qty":4,"name":"Ichor Wellspring"},{"qty":2,"name":"Makeshift Munitions"},{"qty":4,"name":"Myr Enforcer"},{"qty":4,"name":"Seat of the Synod"},{"qty":4,"name":"Terrarion"},{"qty":4,"name":"Thoughtcast"},{"qty":4,"name":"Vault of Whispers"}],"side":[{"qty":3,"name":"Gorilla Shaman"},{"qty":2,"name":"Gurmag Angler"},{"qty":4,"name":"Krark-Clan Shaman"},{"qty":1,"name":"Nihil Spellbomb"},{"qty":3,"name":"Pyroblast"},{"qty":2,"name":"Red Elemental Blast"}]}}