{"id":"6350325","archetype":"Brew Jund","url":"https://www.mtggoldfish.com/deck/6350325","pilot":"tilt_aint_sexy","place":"44th","tournament_name":"Pauper Challenge 32 2024-04-27","tournament_date":"2024-04-27","mtgo_price":25,"tabletop_price":40,"decklist":{"main":[{"qty":4,"name":"Basking Rootwalla"},{"qty":2,"name":"Commune with the Gods"},{"qty":4,"name":"Dread Return"},{"qty":4,"name":"Faithless Looting"},{"qty":1,"name":"Flaring Pain"},{"qty":5,"name":"Forest"},{"qty":4,"name":"Generous Ent"},{"qty":2,"name":"Geothermal Bog"},{"qty":4,"name":"Hangar Scrounger"},{"qty":2,"name":"Haunted Mire"},{"qty":4,"name":"Lotleth Giant"},{"qty":5,"name":"Mountain"},{"qty":4,"name":"Oliphaunt"},{"qty":4,"name":"Rubblebelt Maverick"},{"qty":4,"name":"Scrapwork Mutt"},{"qty":4,"name":"Seeker of Skybreak"},{"qty":2,"name":"Unearth"},{"qty":1,"name":"Weather the Storm"}],"side":[{"qty":3,"name":"Ancient Grudge"},{"qty":3,"name":"Faerie Macabre"},{"qty":3,"name":"Fiery Cannonade"},{"qty":1,"name":"Flaring Pain"},{"qty":2,"name":"Pyroblast"},{"qty":2,"name":"Ray of Revelation"},{"qty":1,"name":"Weather the Storm"}]}}