{"id":"7240773","archetype":"Burn","url":"https://www.mtggoldfish.com/deck/7240773","pilot":"VaT 69","place":"1 - 3","tournament_name":"Weekly Pauper\n","tournament_date":"2025-07-15","mtgo_price":73,"tabletop_price":63,"decklist":{"main":[{"qty":4,"name":"Burning-Tree Emissary"},{"qty":2,"name":"Chain Lightning"},{"qty":4,"name":"Clockwork Percussionist"},{"qty":3,"name":"Experimental Synthesizer"},{"qty":1,"name":"Fireblast"},{"qty":4,"name":"Galvanic Blast"},{"qty":4,"name":"Goblin Bushwhacker"},{"qty":4,"name":"Goblin Tomb Raider"},{"qty":4,"name":"Great Furnace"},{"qty":4,"name":"Lightning Bolt"},{"qty":14,"name":"Mountain"},{"qty":4,"name":"Rally at the Hornburg"},{"qty":2,"name":"Reckless Impulse"},{"qty":4,"name":"Voldaren Epicure"},{"qty":2,"name":"Wrenn's Resolve"}],"side":[{"qty":2,"name":"Cast into the Fire"},{"qty":2,"name":"Electrickery"},{"qty":1,"name":"End the Festivities"},{"qty":1,"name":"Flaring Pain"},{"qty":4,"name":"Pyroblast"},{"qty":1,"name":"Relic of Progenitus"},{"qty":2,"name":"Searing Blaze"},{"qty":2,"name":"Smash to Smithereens"}]}}