{"id":"7619507","archetype":"Elves","url":"https://www.mtggoldfish.com/deck/7619507","pilot":"KeesKloost","place":"3 - 2","tournament_name":"WPC Winter Ed. 2026\n","tournament_date":"2026-02-07","mtgo_price":172,"tabletop_price":110,"decklist":{"main":[{"qty":4,"name":"Avenging Hunter"},{"qty":4,"name":"Elvish Mystic"},{"qty":8,"name":"Forest"},{"qty":4,"name":"Generous Ent"},{"qty":4,"name":"Land Grant"},{"qty":4,"name":"Lead the Stampede"},{"qty":4,"name":"Llanowar Elves"},{"qty":2,"name":"Masked Vandal"},{"qty":4,"name":"Nyxborn Hydra"},{"qty":4,"name":"Priest of Titania"},{"qty":4,"name":"Quirion Ranger"},{"qty":4,"name":"Sagu Wildling"},{"qty":4,"name":"Timberwatch Elf"},{"qty":2,"name":"Wellwisher"},{"qty":4,"name":"Winding Way"}],"side":[{"qty":3,"name":"Faerie Macabre"},{"qty":4,"name":"Gut Shot"},{"qty":2,"name":"Masked Vandal"},{"qty":4,"name":"Vitu-Ghazi Inspector"},{"qty":2,"name":"Wellwisher"}]}}