{"id":"7711366","archetype":"MonoR Dredge","pilot":null,"place":null,"tournament_name":null,"tournament_date":null,"mtgo_price":null,"tabletop_price":null,"decklist":{"main":[{"qty":4,"name":"Cathartic Reunion"},{"qty":3,"name":"Dread Return"},{"qty":4,"name":"Faithless Looting"},{"qty":3,"name":"Fiery Temper"},{"qty":2,"name":"Hidden Grotto"},{"qty":2,"name":"Insolent Neonate"},{"qty":3,"name":"Lotleth Giant"},{"qty":4,"name":"Molten Gatekeeper"},{"qty":4,"name":"Mountain"},{"qty":4,"name":"Mountain"},{"qty":4,"name":"Mountain"},{"qty":2,"name":"Oliphaunt"},{"qty":1,"name":"Oliphaunt"},{"qty":4,"name":"Scrapwork Mutt"},{"qty":4,"name":"Sneaky Snacker"},{"qty":4,"name":"Stinkweed Imp"},{"qty":4,"name":"Stormshriek Feral"},{"qty":4,"name":"Voldaren Epicure"}],"side":[{"qty":4,"name":"Breath Weapon"},{"qty":4,"name":"Red Elemental Blast"},{"qty":4,"name":"Siege Smash"},{"qty":3,"name":"Tormod's Crypt"}]}}