{"name":"Aureliano Rossi","slug":"Aureliano_Rossi","deckCount":2,"archetypeCount":1,"firstSeen":"2023-09-19","lastSeen":"2023-10-03","archetypes":["Dimir Terror"],"decks":[{"id":"5975180","url":"https://www.mtggoldfish.com/deck/5975180","archetype":"Dimir Terror","place":"4th","tournament_name":"4° Tappa - Season 1 - Road to Paupergeddon Winter edition 2023 @ Lega Pauper Merate","tournament_date":"2023-10-03"},{"id":"5880229","url":"https://www.mtggoldfish.com/deck/5880229","archetype":"Dimir Terror","place":"3rd","tournament_name":"2° Tappa - Season 1 - Road to Paupergeddon Winter edition 2023 @ Lega Pauper Merate","tournament_date":"2023-09-19"}]}