{"name":"eggBR","slug":"eggBR","deckCount":21,"archetypeCount":3,"firstSeen":"2025-09-16","lastSeen":"2026-05-19","archetypes":["MonoR Blitz","MonoR Madness","Rakdos Burn"],"decks":[{"id":"7794083","url":"https://www.mtggoldfish.com/deck/7794083","archetype":"Rakdos Burn","place":"4 - 0","tournament_name":"Mont Weekly Pauper \n","tournament_date":"2026-05-19"},{"id":"7779994","url":"https://www.mtggoldfish.com/deck/7779994","archetype":"MonoR Madness","place":"3 - 1","tournament_name":"Mont Weekly Pauper\n","tournament_date":"2026-05-12"},{"id":"7768990","url":"https://www.mtggoldfish.com/deck/7768990","archetype":"Rakdos Burn","place":"2 - 2","tournament_name":"4 Etapa CLM Pauper\n","tournament_date":"2026-05-05"},{"id":"7746951","url":"https://www.mtggoldfish.com/deck/7746951","archetype":"MonoR Blitz","place":"-","tournament_name":"Mont Weekly Pauper\n","tournament_date":"2026-04-21"},{"id":"7736061","url":"https://www.mtggoldfish.com/deck/7736061","archetype":"Rakdos Burn","place":"4 - 0","tournament_name":"3 Etapa CLM Pauper\n","tournament_date":"2026-04-14"},{"id":"7722484","url":"https://www.mtggoldfish.com/deck/7722484","archetype":"Rakdos Burn","place":"-","tournament_name":"Mont Weekly Pauper\n","tournament_date":"2026-04-07"},{"id":"7700570","url":"https://www.mtggoldfish.com/deck/7700570","archetype":"Rakdos Burn","place":"2 - 2","tournament_name":"Mont Weekly Pauper\n","tournament_date":"2026-03-24"},{"id":"7679264","url":"https://www.mtggoldfish.com/deck/7679264","archetype":"Rakdos Burn","place":"5 - 0","tournament_name":"Pauper League 2026-03-13\n","tournament_date":"2026-03-13"},{"id":"7676979","url":"https://www.mtggoldfish.com/deck/7676979","archetype":"Rakdos Burn","place":"2 - 2","tournament_name":"Mont Weekly Pauper\n","tournament_date":"2026-03-10"},{"id":"7670265","url":"https://www.mtggoldfish.com/deck/7670265","archetype":"Rakdos Burn","place":"5 - 0","tournament_name":"Pauper League 2026-03-08\n","tournament_date":"2026-03-08"},{"id":"7663118","url":"https://www.mtggoldfish.com/deck/7663118","archetype":"Rakdos Burn","place":"2 - 2","tournament_name":"Mont Weekly Pauper\n","tournament_date":"2026-03-03"},{"id":"7657125","url":"https://www.mtggoldfish.com/deck/7657125","archetype":"Rakdos Burn","place":"4 - 0","tournament_name":"\n\n\n\n1 Open MPL - Mont Pauper League \n","tournament_date":"2026-02-28"},{"id":"7650642","url":"https://www.mtggoldfish.com/deck/7650642","archetype":"Rakdos Burn","place":"3 - 1","tournament_name":"Mont Weekly Pauper\n","tournament_date":"2026-02-24"},{"id":"7624239","url":"https://www.mtggoldfish.com/deck/7624239","archetype":"Rakdos Burn","place":"3 - 1","tournament_name":"Mont Weekly Pauper\n","tournament_date":"2026-02-10"},{"id":"7611572","url":"https://www.mtggoldfish.com/deck/7611572","archetype":"Rakdos Burn","place":"2 - 2","tournament_name":"Mont Weekly Pauper\n","tournament_date":"2026-02-03"},{"id":"7581743","url":"https://www.mtggoldfish.com/deck/7581743","archetype":"Rakdos Burn","place":"5 - 0","tournament_name":"Pauper League 2026-01-20\n","tournament_date":"2026-01-20"},{"id":"7558568","url":"https://www.mtggoldfish.com/deck/7558568","archetype":"Rakdos Burn","place":"2 - 2","tournament_name":"Mont Weekly Pauper\n","tournament_date":"2026-01-06"},{"id":"7557058","url":"https://www.mtggoldfish.com/deck/7557058","archetype":"Rakdos Burn","place":"3rd","tournament_name":"FUGUETE CHAMP 272\n","tournament_date":"2025-12-30"},{"id":"7371282","url":"https://www.mtggoldfish.com/deck/7371282","archetype":"Rakdos Burn","place":"3 - 1","tournament_name":"Mont Weekly Pauper \n","tournament_date":"2025-09-30"},{"id":"7359407","url":"https://www.mtggoldfish.com/deck/7359407","archetype":"Rakdos Burn","place":"3 - 1","tournament_name":"Mont Weekly Pauper \n","tournament_date":"2025-09-23"},{"id":"7348595","url":"https://www.mtggoldfish.com/deck/7348595","archetype":"Rakdos Burn","place":"2 - 2","tournament_name":"Mont Weekly Pauper \n","tournament_date":"2025-09-16"}]}