{"name":"Espo1991","slug":"Espo1991","deckCount":2,"archetypeCount":2,"firstSeen":"2012-09-30","lastSeen":"2012-10-04","archetypes":["Infect","Izzet 8-Post"],"decks":[{"id":"168278","url":"https://www.mtggoldfish.com/deck/168278","archetype":"Infect","place":"3 - 1","tournament_name":"Pauper Daily #4413713","tournament_date":"2012-10-04"},{"id":"167427","url":"https://www.mtggoldfish.com/deck/167427","archetype":"Izzet 8-Post","place":"3 - 1","tournament_name":"Pauper Daily #4392602","tournament_date":"2012-09-30"}]}