{"name":"LordMendigao","slug":"LordMendigao","deckCount":4,"archetypeCount":1,"firstSeen":"2025-10-03","lastSeen":"2025-11-12","archetypes":["MonoU Terror"],"decks":[{"id":"7449391","url":"https://www.mtggoldfish.com/deck/7449391","archetype":"MonoU Terror","place":"31st","tournament_name":"Pauper Challenge 32 Special 2025-11-12\n","tournament_date":"2025-11-12"},{"id":"7397550","url":"https://www.mtggoldfish.com/deck/7397550","archetype":"MonoU Terror","place":"5 - 0","tournament_name":"Pauper League 2025-10-16\n","tournament_date":"2025-10-16"},{"id":"7379552","url":"https://www.mtggoldfish.com/deck/7379552","archetype":"MonoU Terror","place":"22nd","tournament_name":"Pauper Challenge 32 2025-10-05\n","tournament_date":"2025-10-05"},{"id":"7375222","url":"https://www.mtggoldfish.com/deck/7375222","archetype":"MonoU Terror","place":"27th","tournament_name":"Pauper Challenge 32 2025-10-03\n","tournament_date":"2025-10-03"}]}