{"name":"PabloCorrea","slug":"PabloCorrea","deckCount":3,"archetypeCount":3,"firstSeen":"2025-09-14","lastSeen":"2025-11-30","archetypes":["Affinity","Elves","Rakdos Burn"],"decks":[{"id":"7487752","url":"https://www.mtggoldfish.com/deck/7487752","archetype":"Affinity","place":"35th","tournament_name":"\n\n\n\tLiga Gaucha de Pauper 2025 - Etapa 10\n","tournament_date":"2025-11-30"},{"id":"7406319","url":"https://www.mtggoldfish.com/deck/7406319","archetype":"Elves","place":"4 - 3","tournament_name":"Liga Gaucha de Pauper 2025 - Etapa 9\n","tournament_date":"2025-10-20"},{"id":"7345918","url":"https://www.mtggoldfish.com/deck/7345918","archetype":"Rakdos Burn","place":"1 - 6","tournament_name":"\n\n\nLiga Gaucha de Pauper 2025 - Etapa 8\n","tournament_date":"2025-09-14"}]}