{"name":"Incogneato","slug":"Incogneato","deckCount":2,"archetypeCount":2,"firstSeen":"2019-03-17","lastSeen":"2019-03-24","archetypes":["Bogles","MonoB Control"],"decks":[{"id":"1741860","url":"https://www.mtggoldfish.com/deck/1741860","archetype":"Bogles","place":"4 - 2","tournament_name":"Pauper Challenge #11829473","tournament_date":"2019-03-24"},{"id":"1726756","url":"https://www.mtggoldfish.com/deck/1726756","archetype":"MonoB Control","place":"3 - 3","tournament_name":"Pauper Challenge #11823870","tournament_date":"2019-03-17"}]}