{"name":"Rifter9","slug":"Rifter9","deckCount":3,"archetypeCount":1,"firstSeen":"2011-07-02","lastSeen":"2011-10-25","archetypes":["Izzet 8-Post"],"decks":[{"id":"71285","url":"https://www.mtggoldfish.com/deck/71285","archetype":"Izzet 8-Post","place":"3 - 1","tournament_name":"Pauper Daily #2925902","tournament_date":"2011-10-25"},{"id":"69045","url":"https://www.mtggoldfish.com/deck/69045","archetype":"Izzet 8-Post","place":"3 - 1","tournament_name":"Pauper Daily #2890879","tournament_date":"2011-10-11"},{"id":"43415","url":"https://www.mtggoldfish.com/deck/43415","archetype":"Izzet 8-Post","place":"4 - 0","tournament_name":"Pauper Daily #2536975","tournament_date":"2011-07-02"}]}