{
    "archetypes": {
        "py/set": [
            "MonoB Ponza",
            "MonoB Burn",
            "Dimir Flicker",
            "Dimir Control",
            "MonoB Control"
        ]
    },
    "name": "Debt to the Kami",
    "scryfall": {
        "arena_id": 79517,
        "artist": "Jodie Muir",
        "artist_ids": [
            "b09e6cd1-0257-425a-9bbb-5cac3f803443"
        ],
        "booster": true,
        "border_color": "black",
        "card_back_id": "0aeebaf5-8c7d-4636-9e82-8c27447861f7",
        "cardmarket_id": 608211,
        "cmc": 3.0,
        "collector_number": "92",
        "color_identity": [
            "B"
        ],
        "colors": [
            "B"
        ],
        "digital": false,
        "edhrec_rank": 11225,
        "finishes": [
            "nonfoil",
            "foil"
        ],
        "flavor_text": "The masters weren't speaking figuratively when they said guilt could be all-consuming.",
        "foil": true,
        "frame": "2015",
        "full_art": false,
        "games": [
            "paper",
            "mtgo",
            "arena"
        ],
        "highres_image": true,
        "id": "c1a7e728-ba01-4e3d-b269-9e2dd85a1d1b",
        "illustration_id": "8fa1d96b-ff7d-4889-a55a-a46d4c896d95",
        "image_status": "highres_scan",
        "image_uris": {
            "art_crop": "https://cards.scryfall.io/art_crop/front/c/1/c1a7e728-ba01-4e3d-b269-9e2dd85a1d1b.jpg?1654567093",
            "border_crop": "https://cards.scryfall.io/border_crop/front/c/1/c1a7e728-ba01-4e3d-b269-9e2dd85a1d1b.jpg?1654567093",
            "large": "https://cards.scryfall.io/large/front/c/1/c1a7e728-ba01-4e3d-b269-9e2dd85a1d1b.jpg?1654567093",
            "normal": "https://cards.scryfall.io/normal/front/c/1/c1a7e728-ba01-4e3d-b269-9e2dd85a1d1b.jpg?1654567093",
            "png": "https://cards.scryfall.io/png/front/c/1/c1a7e728-ba01-4e3d-b269-9e2dd85a1d1b.png?1654567093",
            "small": "https://cards.scryfall.io/small/front/c/1/c1a7e728-ba01-4e3d-b269-9e2dd85a1d1b.jpg?1654567093"
        },
        "keywords": [],
        "lang": "en",
        "layout": "normal",
        "legalities": {
            "alchemy": "not_legal",
            "brawl": "legal",
            "commander": "legal",
            "duel": "legal",
            "explorer": "legal",
            "future": "not_legal",
            "gladiator": "legal",
            "historic": "legal",
            "legacy": "legal",
            "modern": "legal",
            "oathbreaker": "legal",
            "oldschool": "not_legal",
            "pauper": "legal",
            "paupercommander": "legal",
            "penny": "legal",
            "pioneer": "legal",
            "predh": "not_legal",
            "premodern": "not_legal",
            "standard": "legal",
            "standardbrawl": "legal",
            "timeless": "legal",
            "vintage": "legal"
        },
        "mana_cost": "{2}{B}",
        "mtgo_id": 97104,
        "multiverse_ids": [
            548390
        ],
        "name": "Debt to the Kami",
        "nonfoil": true,
        "object": "card",
        "oracle_id": "c6c1e576-7197-4067-8cd1-aa535188e1b8",
        "oracle_text": "Choose one \u2014\n\u2022 Target opponent exiles a creature they control.\n\u2022 Target opponent exiles an enchantment they control.",
        "oversized": false,
        "penny_rank": 3803,
        "prices": {
            "eur": "0.09",
            "eur_foil": "0.15",
            "tix": "0.01",
            "usd": "0.09",
            "usd_etched": null,
            "usd_foil": "0.18"
        },
        "prints_search_uri": "https://api.scryfall.com/cards/search?order=released&q=oracleid%3Ac6c1e576-7197-4067-8cd1-aa535188e1b8&unique=prints",
        "promo": false,
        "purchase_uris": {
            "cardhoarder": "https://www.cardhoarder.com/cards/97104?affiliate_id=scryfall&ref=card-profile&utm_campaign=affiliate&utm_medium=card&utm_source=scryfall",
            "cardmarket": "https://www.cardmarket.com/en/Magic/Products/Singles/Kamigawa-Neon-Dynasty/Debt-to-the-Kami?referrer=scryfall&utm_campaign=card_prices&utm_medium=text&utm_source=scryfall",
            "tcgplayer": "https://tcgplayer.pxf.io/c/4931599/1830156/21018?subId1=api&u=https%3A%2F%2Fwww.tcgplayer.com%2Fproduct%2F262861%3Fpage%3D1"
        },
        "rarity": "common",
        "related_uris": {
            "edhrec": "https://edhrec.com/route/?cc=Debt+to+the+Kami",
            "gatherer": "https://gatherer.wizards.com/Pages/Card/Details.aspx?multiverseid=548390&printed=false",
            "tcgplayer_infinite_articles": "https://tcgplayer.pxf.io/c/4931599/1830156/21018?subId1=api&trafcat=infinite&u=https%3A%2F%2Finfinite.tcgplayer.com%2Fsearch%3FcontentMode%3Darticle%26game%3Dmagic%26partner%3Dscryfall%26q%3DDebt%2Bto%2Bthe%2BKami",
            "tcgplayer_infinite_decks": "https://tcgplayer.pxf.io/c/4931599/1830156/21018?subId1=api&trafcat=infinite&u=https%3A%2F%2Finfinite.tcgplayer.com%2Fsearch%3FcontentMode%3Ddeck%26game%3Dmagic%26partner%3Dscryfall%26q%3DDebt%2Bto%2Bthe%2BKami"
        },
        "released_at": "2022-02-18",
        "reprint": false,
        "reserved": false,
        "rulings_uri": "https://api.scryfall.com/cards/c1a7e728-ba01-4e3d-b269-9e2dd85a1d1b/rulings",
        "scryfall_set_uri": "https://scryfall.com/sets/neo?utm_source=api",
        "scryfall_uri": "https://scryfall.com/card/neo/92/debt-to-the-kami?utm_source=api",
        "set": "neo",
        "set_id": "59a2059f-5482-433f-8761-eb2e17859b71",
        "set_name": "Kamigawa: Neon Dynasty",
        "set_search_uri": "https://api.scryfall.com/cards/search?order=set&q=e%3Aneo&unique=prints",
        "set_type": "expansion",
        "set_uri": "https://api.scryfall.com/sets/59a2059f-5482-433f-8761-eb2e17859b71",
        "story_spotlight": false,
        "tcgplayer_id": 262861,
        "textless": false,
        "type_line": "Instant",
        "uri": "https://api.scryfall.com/cards/c1a7e728-ba01-4e3d-b269-9e2dd85a1d1b",
        "variation": false
    }
}