{
    "archetypes": {
        "py/set": []
    },
    "scryfall": {
        "arena_id": 83839,
        "artist": "Maxime Minard",
        "artist_ids": [
            "a9065769-afcd-4e54-a3c0-5809e7b4108b"
        ],
        "booster": true,
        "border_color": "black",
        "card_back_id": "0aeebaf5-8c7d-4636-9e82-8c27447861f7",
        "cardmarket_id": 694754,
        "cmc": 3.0,
        "collector_number": "139",
        "color_identity": [
            "R"
        ],
        "colors": [
            "R"
        ],
        "digital": false,
        "edhrec_rank": 22084,
        "finishes": [
            "nonfoil",
            "foil"
        ],
        "flavor_text": "You would laugh too if you just burned through a tyrranax's stomach.",
        "foil": true,
        "frame": "2015",
        "full_art": false,
        "game_changer": false,
        "games": [
            "paper",
            "arena",
            "mtgo"
        ],
        "highres_image": true,
        "id": "f7155c42-a824-4bbe-9f7a-fa01e7625fd6",
        "illustration_id": "04adae8d-02e5-4952-90fd-bfb61705ac24",
        "image_status": "highres_scan",
        "image_uris": {
            "art_crop": "https://cards.scryfall.io/art_crop/front/f/7/f7155c42-a824-4bbe-9f7a-fa01e7625fd6.jpg?1675957096",
            "border_crop": "https://cards.scryfall.io/border_crop/front/f/7/f7155c42-a824-4bbe-9f7a-fa01e7625fd6.jpg?1675957096",
            "large": "https://cards.scryfall.io/large/front/f/7/f7155c42-a824-4bbe-9f7a-fa01e7625fd6.jpg?1675957096",
            "normal": "https://cards.scryfall.io/normal/front/f/7/f7155c42-a824-4bbe-9f7a-fa01e7625fd6.jpg?1675957096",
            "png": "https://cards.scryfall.io/png/front/f/7/f7155c42-a824-4bbe-9f7a-fa01e7625fd6.png?1675957096",
            "small": "https://cards.scryfall.io/small/front/f/7/f7155c42-a824-4bbe-9f7a-fa01e7625fd6.jpg?1675957096"
        },
        "keywords": [
            "Trample"
        ],
        "lang": "en",
        "layout": "normal",
        "legalities": {
            "alchemy": "not_legal",
            "brawl": "legal",
            "commander": "legal",
            "duel": "legal",
            "future": "not_legal",
            "gladiator": "legal",
            "historic": "legal",
            "legacy": "legal",
            "modern": "legal",
            "oathbreaker": "legal",
            "oldschool": "not_legal",
            "pauper": "legal",
            "paupercommander": "legal",
            "penny": "not_legal",
            "pioneer": "legal",
            "predh": "not_legal",
            "premodern": "not_legal",
            "standard": "not_legal",
            "standardbrawl": "not_legal",
            "timeless": "legal",
            "tlr": "legal",
            "vintage": "legal"
        },
        "mana_cost": "{2}{R}",
        "mtgo_id": 106493,
        "multiverse_ids": [
            602669
        ],
        "name": "Kuldotha Cackler",
        "nonfoil": true,
        "object": "card",
        "oracle_id": "e1a41091-6ff1-42bb-b248-90040107efe1",
        "oracle_text": "Trample\nWhenever this creature attacks, it gets +X/+0 until end of turn, where X is the number of permanents you control with oil counters on them.",
        "oversized": false,
        "power": "2",
        "prices": {
            "eur": "0.04",
            "eur_foil": "0.05",
            "tix": "0.03",
            "usd": "0.10",
            "usd_etched": null,
            "usd_foil": "0.09"
        },
        "prints_search_uri": "https://api.scryfall.com/cards/search?order=released&q=oracleid%3Ae1a41091-6ff1-42bb-b248-90040107efe1&unique=prints",
        "promo": false,
        "purchase_uris": {
            "cardhoarder": "https://www.cardhoarder.com/cards/106493?affiliate_id=scryfall&ref=card-profile&utm_campaign=affiliate&utm_medium=card&utm_source=scryfall",
            "cardmarket": "https://www.cardmarket.com/en/Magic/Products?idProduct=694754&referrer=scryfall&utm_campaign=card_prices&utm_medium=text&utm_source=scryfall",
            "tcgplayer": "https://partner.tcgplayer.com/c/4931599/1830156/21018?subId1=api&u=https%3A%2F%2Fwww.tcgplayer.com%2Fproduct%2F479601%3Fpage%3D1"
        },
        "rarity": "common",
        "related_uris": {
            "edhrec": "https://edhrec.com/route/?cc=Kuldotha+Cackler",
            "gatherer": "https://gatherer.wizards.com/Pages/Card/Details.aspx?multiverseid=602669&printed=false",
            "tcgplayer_infinite_articles": "https://partner.tcgplayer.com/c/4931599/1830156/21018?subId1=api&trafcat=tcgplayer.com%2Fsearch%2Farticles&u=https%3A%2F%2Fwww.tcgplayer.com%2Fsearch%2Farticles%3FproductLineName%3Dmagic%26q%3DKuldotha%2BCackler",
            "tcgplayer_infinite_decks": "https://partner.tcgplayer.com/c/4931599/1830156/21018?subId1=api&trafcat=tcgplayer.com%2Fsearch%2Fdecks&u=https%3A%2F%2Fwww.tcgplayer.com%2Fsearch%2Fdecks%3FproductLineName%3Dmagic%26q%3DKuldotha%2BCackler"
        },
        "released_at": "2023-02-10",
        "reprint": false,
        "reserved": false,
        "rulings_uri": "https://api.scryfall.com/cards/f7155c42-a824-4bbe-9f7a-fa01e7625fd6/rulings",
        "scryfall_set_uri": "https://scryfall.com/sets/one?utm_source=api",
        "scryfall_uri": "https://scryfall.com/card/one/139/kuldotha-cackler?utm_source=api",
        "set": "one",
        "set_id": "04bef644-343f-4230-95ee-255f29aa67a2",
        "set_name": "Phyrexia: All Will Be One",
        "set_search_uri": "https://api.scryfall.com/cards/search?order=set&q=e%3Aone&unique=prints",
        "set_type": "expansion",
        "set_uri": "https://api.scryfall.com/sets/04bef644-343f-4230-95ee-255f29aa67a2",
        "story_spotlight": false,
        "tcgplayer_id": 479601,
        "textless": false,
        "toughness": "3",
        "type_line": "Creature \u2014 Phyrexian Hyena",
        "uri": "https://api.scryfall.com/cards/f7155c42-a824-4bbe-9f7a-fa01e7625fd6",
        "variation": false
    }
}