{
    "archetypes": {
        "py/set": []
    },
    "scryfall": {
        "artist": "Zoltan Boros & Gabor Szikszai",
        "artist_ids": [
            "1885e6cb-c827-4896-994e-3d0a027d602f",
            "44c3877f-8771-43dc-9e40-f4c765f59d2e"
        ],
        "booster": false,
        "border_color": "black",
        "card_back_id": "0aeebaf5-8c7d-4636-9e82-8c27447861f7",
        "cardmarket_id": 320657,
        "cmc": 3.0,
        "collector_number": "59",
        "color_identity": [
            "U"
        ],
        "colors": [],
        "digital": false,
        "edhrec_rank": 23404,
        "finishes": [
            "nonfoil"
        ],
        "flavor_text": "All the curiosity of the Neurok with only a trace of their duplicity.",
        "foil": false,
        "frame": "2015",
        "full_art": false,
        "games": [
            "paper"
        ],
        "highres_image": true,
        "id": "76114dda-811c-41b2-995b-9e80115cc8c8",
        "illustration_id": "177f00be-7c51-408d-9bd4-52ee1237c090",
        "image_status": "highres_scan",
        "image_uris": {
            "art_crop": "https://cards.scryfall.io/art_crop/front/7/6/76114dda-811c-41b2-995b-9e80115cc8c8.jpg?1561759254",
            "border_crop": "https://cards.scryfall.io/border_crop/front/7/6/76114dda-811c-41b2-995b-9e80115cc8c8.jpg?1561759254",
            "large": "https://cards.scryfall.io/large/front/7/6/76114dda-811c-41b2-995b-9e80115cc8c8.jpg?1561759254",
            "normal": "https://cards.scryfall.io/normal/front/7/6/76114dda-811c-41b2-995b-9e80115cc8c8.jpg?1561759254",
            "png": "https://cards.scryfall.io/png/front/7/6/76114dda-811c-41b2-995b-9e80115cc8c8.png?1561759254",
            "small": "https://cards.scryfall.io/small/front/7/6/76114dda-811c-41b2-995b-9e80115cc8c8.jpg?1561759254"
        },
        "keywords": [],
        "lang": "en",
        "layout": "normal",
        "legalities": {
            "alchemy": "not_legal",
            "brawl": "not_legal",
            "commander": "legal",
            "duel": "legal",
            "explorer": "not_legal",
            "future": "not_legal",
            "gladiator": "not_legal",
            "historic": "not_legal",
            "legacy": "legal",
            "modern": "legal",
            "oathbreaker": "legal",
            "oldschool": "not_legal",
            "pauper": "legal",
            "paupercommander": "legal",
            "penny": "legal",
            "pioneer": "not_legal",
            "predh": "legal",
            "premodern": "not_legal",
            "standard": "not_legal",
            "standardbrawl": "not_legal",
            "timeless": "not_legal",
            "vintage": "legal"
        },
        "mana_cost": "{3}",
        "multiverse_ids": [
            442795
        ],
        "name": "Neurok Replica",
        "nonfoil": true,
        "object": "card",
        "oracle_id": "de8cdbd4-d8f7-4ce8-a69b-6d2020beff63",
        "oracle_text": "{1}{U}, Sacrifice Neurok Replica: Return target creature to its owner's hand.",
        "oversized": false,
        "penny_rank": 15314,
        "power": "1",
        "prices": {
            "eur": "0.14",
            "eur_foil": null,
            "tix": null,
            "usd": "0.14",
            "usd_etched": null,
            "usd_foil": null
        },
        "prints_search_uri": "https://api.scryfall.com/cards/search?order=released&q=oracleid%3Ade8cdbd4-d8f7-4ce8-a69b-6d2020beff63&unique=prints",
        "promo": false,
        "purchase_uris": {
            "cardhoarder": "https://www.cardhoarder.com/cards?affiliate_id=scryfall&data%5Bsearch%5D=Neurok+Replica&ref=card-profile&utm_campaign=affiliate&utm_medium=card&utm_source=scryfall",
            "cardmarket": "https://www.cardmarket.com/en/Magic/Products/Singles/Duel-Decks-Elves-vs-Inventors/Neurok-Replica?referrer=scryfall&utm_campaign=card_prices&utm_medium=text&utm_source=scryfall",
            "tcgplayer": "https://tcgplayer.pxf.io/c/4931599/1830156/21018?subId1=api&u=https%3A%2F%2Fwww.tcgplayer.com%2Fproduct%2F162872%3Fpage%3D1"
        },
        "rarity": "common",
        "related_uris": {
            "edhrec": "https://edhrec.com/route/?cc=Neurok+Replica",
            "gatherer": "https://gatherer.wizards.com/Pages/Card/Details.aspx?multiverseid=442795&printed=false",
            "tcgplayer_infinite_articles": "https://tcgplayer.pxf.io/c/4931599/1830156/21018?subId1=api&trafcat=infinite&u=https%3A%2F%2Finfinite.tcgplayer.com%2Fsearch%3FcontentMode%3Darticle%26game%3Dmagic%26partner%3Dscryfall%26q%3DNeurok%2BReplica",
            "tcgplayer_infinite_decks": "https://tcgplayer.pxf.io/c/4931599/1830156/21018?subId1=api&trafcat=infinite&u=https%3A%2F%2Finfinite.tcgplayer.com%2Fsearch%3FcontentMode%3Ddeck%26game%3Dmagic%26partner%3Dscryfall%26q%3DNeurok%2BReplica"
        },
        "released_at": "2018-04-06",
        "reprint": true,
        "reserved": false,
        "rulings_uri": "https://api.scryfall.com/cards/76114dda-811c-41b2-995b-9e80115cc8c8/rulings",
        "scryfall_set_uri": "https://scryfall.com/sets/ddu?utm_source=api",
        "scryfall_uri": "https://scryfall.com/card/ddu/59/neurok-replica?utm_source=api",
        "set": "ddu",
        "set_id": "01e30e53-f292-4c39-ab09-435b015877f5",
        "set_name": "Duel Decks: Elves vs. Inventors",
        "set_search_uri": "https://api.scryfall.com/cards/search?order=set&q=e%3Addu&unique=prints",
        "set_type": "duel_deck",
        "set_uri": "https://api.scryfall.com/sets/01e30e53-f292-4c39-ab09-435b015877f5",
        "story_spotlight": false,
        "tcgplayer_id": 162872,
        "textless": false,
        "toughness": "4",
        "type_line": "Artifact Creature \u2014 Wizard",
        "uri": "https://api.scryfall.com/cards/76114dda-811c-41b2-995b-9e80115cc8c8",
        "variation": false
    }
}