{
    "archetypes": {
        "py/set": [
            "Trinket Control",
            "Jeskai Glitters",
            "Flicker Tron",
            "Brew Sultai"
        ]
    },
    "scryfall": {
        "artist": "Mark A. Nelson",
        "artist_ids": [
            "a10f59a4-36fd-4ef3-966b-5570ca118062"
        ],
        "booster": false,
        "border_color": "black",
        "card_back_id": "0aeebaf5-8c7d-4636-9e82-8c27447861f7",
        "cmc": 3.0,
        "collector_number": "6",
        "color_identity": [
            "U"
        ],
        "colors": [
            "U"
        ],
        "digital": true,
        "edhrec_rank": 1942,
        "finishes": [
            "nonfoil"
        ],
        "foil": false,
        "frame": "2015",
        "full_art": false,
        "game_changer": false,
        "games": [
            "arena"
        ],
        "highres_image": true,
        "id": "c0b7e56a-b983-4645-865f-0c255d58d7ae",
        "illustration_id": "269bd5b7-7f7a-481d-a6e9-6bf5088bc826",
        "image_status": "highres_scan",
        "image_uris": {
            "art_crop": "https://cards.scryfall.io/art_crop/front/c/0/c0b7e56a-b983-4645-865f-0c255d58d7ae.jpg?1755542954",
            "border_crop": "https://cards.scryfall.io/border_crop/front/c/0/c0b7e56a-b983-4645-865f-0c255d58d7ae.jpg?1755542954",
            "large": "https://cards.scryfall.io/large/front/c/0/c0b7e56a-b983-4645-865f-0c255d58d7ae.jpg?1755542954",
            "normal": "https://cards.scryfall.io/normal/front/c/0/c0b7e56a-b983-4645-865f-0c255d58d7ae.jpg?1755542954",
            "png": "https://cards.scryfall.io/png/front/c/0/c0b7e56a-b983-4645-865f-0c255d58d7ae.png?1755542954",
            "small": "https://cards.scryfall.io/small/front/c/0/c0b7e56a-b983-4645-865f-0c255d58d7ae.jpg?1755542954"
        },
        "keywords": [],
        "lang": "en",
        "layout": "normal",
        "legalities": {
            "alchemy": "not_legal",
            "brawl": "legal",
            "commander": "legal",
            "duel": "legal",
            "future": "not_legal",
            "gladiator": "legal",
            "historic": "legal",
            "legacy": "legal",
            "modern": "legal",
            "oathbreaker": "legal",
            "oldschool": "not_legal",
            "pauper": "legal",
            "paupercommander": "legal",
            "penny": "not_legal",
            "pioneer": "not_legal",
            "predh": "legal",
            "premodern": "not_legal",
            "standard": "not_legal",
            "standardbrawl": "not_legal",
            "timeless": "legal",
            "tlr": "legal",
            "vintage": "legal"
        },
        "mana_cost": "{2}{U}",
        "multiverse_ids": [],
        "name": "Trinket Mage",
        "nonfoil": true,
        "object": "card",
        "oracle_id": "ffc95093-24a2-4616-a44a-24788e8df9c8",
        "oracle_text": "When this creature enters, you may search your library for an artifact card with mana value 1 or less, reveal that card, put it into your hand, then shuffle.",
        "oversized": false,
        "penny_rank": 3076,
        "power": "2",
        "prices": {
            "eur": null,
            "eur_foil": null,
            "tix": null,
            "usd": null,
            "usd_etched": null,
            "usd_foil": null
        },
        "prints_search_uri": "https://api.scryfall.com/cards/search?order=released&q=oracleid%3Affc95093-24a2-4616-a44a-24788e8df9c8&unique=prints",
        "promo": false,
        "rarity": "common",
        "related_uris": {
            "edhrec": "https://edhrec.com/route/?cc=Trinket+Mage",
            "tcgplayer_infinite_articles": "https://partner.tcgplayer.com/c/4931599/1830156/21018?subId1=api&trafcat=tcgplayer.com%2Fsearch%2Farticles&u=https%3A%2F%2Fwww.tcgplayer.com%2Fsearch%2Farticles%3FproductLineName%3Dmagic%26q%3DTrinket%2BMage",
            "tcgplayer_infinite_decks": "https://partner.tcgplayer.com/c/4931599/1830156/21018?subId1=api&trafcat=tcgplayer.com%2Fsearch%2Fdecks&u=https%3A%2F%2Fwww.tcgplayer.com%2Fsearch%2Fdecks%3FproductLineName%3Dmagic%26q%3DTrinket%2BMage"
        },
        "released_at": "2025-08-19",
        "reprint": true,
        "reserved": false,
        "rulings_uri": "https://api.scryfall.com/cards/c0b7e56a-b983-4645-865f-0c255d58d7ae/rulings",
        "scryfall_set_uri": "https://scryfall.com/sets/aa2?utm_source=api",
        "scryfall_uri": "https://scryfall.com/card/aa2/6/trinket-mage?utm_source=api",
        "set": "aa2",
        "set_id": "fd3518b9-cf68-447a-a71c-67d36bc56c4d",
        "set_name": "Arena Anthology 2",
        "set_search_uri": "https://api.scryfall.com/cards/search?order=set&q=e%3Aaa2&unique=prints",
        "set_type": "box",
        "set_uri": "https://api.scryfall.com/sets/fd3518b9-cf68-447a-a71c-67d36bc56c4d",
        "story_spotlight": false,
        "textless": false,
        "toughness": "2",
        "type_line": "Creature \u2014 Human Wizard",
        "uri": "https://api.scryfall.com/cards/c0b7e56a-b983-4645-865f-0c255d58d7ae",
        "variation": false
    }
}